invoicely/__init__.py
invoicely/cli.py
invoicely-0.1.0.dist-info/LICENSE
invoicely-0.1.0.dist-info/METADATA
invoicely-0.1.0.dist-info/WHEEL
invoicely-0.1.0.dist-info/entry_points.txt
invoicely-0.1.0.dist-info/top_level.txt
invoicely-0.1.0.dist-info/RECORD
