Metadata-Version: 2.1
Name: invoicely
Version: 0.1.0
Summary: Create simple invoices.
License: MIT License
Project-URL: Homepage, https://github.com/andycaine/invoicely
Project-URL: Documentation, https://github.com/andycaine/invoicely?tab=readme-ov-file#asaa
Project-URL: Repository, https://github.com/andycaine/invoicely.git
Keywords: invoicing,invoices
License-File: LICENSE
Requires-Dist: click
Requires-Dist: reportlab
